Metadata-Version: 2.1
Name: gome-scraper
Version: 1.0.1
Summary: Gome scraper
Home-page: UNKNOWN
Author: DataKund
Author-email: datakund@gmail.com
License: Apache License 2.0
Platform: UNKNOWN
License-File: LICENSE
